cutevariant/__init__.py
cutevariant/__main__.py
cutevariant/bgzf.py
cutevariant/commons.py
cutevariant/config.py
cutevariant/constants.py
cutevariant/default_config.yml
cutevariant/assets/LICENSE
cutevariant/assets/fonts/materialdesignicons-webfont.ttf
cutevariant/assets/i18n/fr.qm
cutevariant/assets/icons/app.png
cutevariant/assets/icons/loading.gif
cutevariant/assets/icons/splash.png
cutevariant/assets/styles/bright.yaml
cutevariant/assets/styles/dark.qss
cutevariant/assets/styles/dark.yaml
cutevariant/assets/styles/frameless.qss
cutevariant/core/__init__.py
cutevariant/core/cli.py
cutevariant/core/command.py
cutevariant/core/querybuilder.py
cutevariant/core/quicksearch.py
cutevariant/core/readerfactory.py
cutevariant/core/report.py
cutevariant/core/sql.py
cutevariant/core/sql_aggregator.py
cutevariant/core/vql.py
cutevariant/core/vql.tx
cutevariant/core/vql.tx.dot.png
cutevariant/core/reader/__init__.py
cutevariant/core/reader/abstractreader.py
cutevariant/core/reader/annotationparser.py
cutevariant/core/reader/bedreader.py
cutevariant/core/reader/csvreader.py
cutevariant/core/reader/fakereader.py
cutevariant/core/reader/pedreader.py
cutevariant/core/reader/vcfreader.py
cutevariant/core/writer/__init__.py
cutevariant/core/writer/abstractwriter.py
cutevariant/core/writer/bedwriter.py
cutevariant/core/writer/csvwriter.py
cutevariant/core/writer/pedwriter.py
cutevariant/core/writer/vcfwriter.py
cutevariant/gui/__init__.py
cutevariant/gui/export.py
cutevariant/gui/ficon.py
cutevariant/gui/formatter.py
cutevariant/gui/mainwindow.py
cutevariant/gui/network.py
cutevariant/gui/plugin.py
cutevariant/gui/plugin_form.py
cutevariant/gui/settings.py
cutevariant/gui/sql_query_model.py
cutevariant/gui/sql_thread.py
cutevariant/gui/style.py
cutevariant/gui/tooltip.py
cutevariant/gui/formatters/cutestyle.py
cutevariant/gui/formatters/default.py
cutevariant/gui/model_view/__init__.py
cutevariant/gui/model_view/pedigree.py
cutevariant/gui/plugins/fields_editor/__init__.py
cutevariant-0.4.5.dist-info/LICENSE
cutevariant-0.4.5.dist-info/METADATA
cutevariant-0.4.5.dist-info/WHEEL
cutevariant-0.4.5.dist-info/entry_points.txt
cutevariant-0.4.5.dist-info/top_level.txt
cutevariant-0.4.5.dist-info/RECORD
