Metadata-Version: 2.1
Name: cutevariant
Version: 0.4.5
Summary: GUI to visualize and process variant data
Home-page: https://github.com/labsquare/cutevariant
Author: Sacha Schutz, Pierre Vignet
Author-email: sacha@labsquare.org
Keywords: GUI,health
Classifier: Development Status :: 4 - Beta
Classifier: Intended Audience :: Science/Research
Classifier: Intended Audience :: Healthcare Industry
Classifier: Programming Language :: Python :: 3
Classifier: Programming Language :: Python :: 3.6
Classifier: Programming Language :: Python :: 3.7
Classifier: Programming Language :: Python :: 3.8
Classifier: License :: OSI Approved :: GNU General Public License v3 or later (GPLv3+)
License-File: LICENSE
Requires-Dist: PySide6 (>=2)
Requires-Dist: PyVCF3 (>=1.0.0)
Requires-Dist: textX (==1.8.0)
Requires-Dist: cachetools (>=4.2.0)
Requires-Dist: jinja2 (>=2.11.3)
Requires-Dist: progressbar2
Requires-Dist: columnar (==1.1.0)
Requires-Dist: numpy (>=1.20)
Requires-Dist: cachetools (>=4.2.2)
Requires-Dist: pyyaml (>=5.4.0)
Requires-Dist: markdown
Provides-Extra: dev
Requires-Dist: pytest-cov (>=2.6.1) ; extra == 'dev'
Requires-Dist: pytest-qt (>=3.2.2) ; extra == 'dev'
Requires-Dist: pytest (>=5.2.0) ; extra == 'dev'
Requires-Dist: schema (==0.7.0) ; extra == 'dev'
Requires-Dist: pytest-runner ; extra == 'dev'
Requires-Dist: zest.releaser[recommended] ; extra == 'dev'
Provides-Extra: doc
Requires-Dist: sphinx ; extra == 'doc'
Requires-Dist: sphinx-rtd-theme ; extra == 'doc'
Requires-Dist: sphinx-argparse ; extra == 'doc'
Requires-Dist: recommonmark (>=0.6) ; extra == 'doc'
